digitalmeve/__init__.py
digitalmeve/cli.py
digitalmeve/core.py
digitalmeve/embedding_pdf.py
digitalmeve/embedding_png.py
digitalmeve/generator.py
digitalmeve/official_identity.py
digitalmeve/pro_identity.py
digitalmeve/utils.py
digitalmeve/verifier.py
digitalmeve-1.7.1.dist-info/licenses/LICENSE
digitalmeve-1.7.1.dist-info/METADATA
digitalmeve-1.7.1.dist-info/WHEEL
digitalmeve-1.7.1.dist-info/entry_points.txt
digitalmeve-1.7.1.dist-info/top_level.txt
digitalmeve-1.7.1.dist-info/RECORD
