Metadata-Version: 2.4
Name: digitalmeve
Version: 1.7.1
Summary: DigitalMeve — The .MEVE Standard: timestamp, hash, and certify digital documents.
Author: DigitalMeve Team
License: DigitalMeve is released under the GNU Affero General Public License v3.0 (AGPL-3.0).
Project-URL: Homepage, https://github.com/BACOUL/digitalmeve
Project-URL: Repository, https://github.com/BACOUL/digitalmeve
Project-URL: Issues, https://github.com/BACOUL/digitalmeve/issues
Project-URL: Documentation, https://github.com/BACOUL/digitalmeve/tree/main/docs
Keywords: proof,verification,hash,timestamp,json,digitalmeve,meve
Classifier: Development Status :: 4 - Beta
Classifier: Intended Audience :: Developers
Classifier: License :: OSI Approved :: MIT License
Classifier: Programming Language :: Python
Classifier: Programming Language :: Python :: 3
Classifier: Programming Language :: Python :: 3.10
Classifier: Programming Language :: Python :: 3.11
Classifier: Programming Language :: Python :: 3.12
Classifier: Topic :: Security :: Cryptography
Classifier: Topic :: Software Development :: Libraries
Classifier: Operating System :: OS Independent
Classifier: Typing :: Typed
Requires-Python: >=3.10
License-File: LICENSE
Requires-Dist: pikepdf>=9.0.0
Requires-Dist: pillow>=10.0.0
Requires-Dist: click>=8.1.7
Dynamic: license-file
